extrap_adaptive_modeler/__init__.py
extrap_adaptive_modeler/data_generator.py
extrap_adaptive_modeler/lazy_tensorflow.py
extrap_adaptive_modeler/load_model.py
extrap_adaptive_modeler/normalizedTerms_newPoints.h5
extrap_adaptive_modeler-1.0.2.dist-info/AUTHORS.md
extrap_adaptive_modeler-1.0.2.dist-info/LICENSE
extrap_adaptive_modeler-1.0.2.dist-info/METADATA
extrap_adaptive_modeler-1.0.2.dist-info/WHEEL
extrap_adaptive_modeler-1.0.2.dist-info/top_level.txt
extrap_adaptive_modeler-1.0.2.dist-info/RECORD
